crystalpol/__init__.py
crystalpol/__main__.py
crystalpol/gaussian.py
crystalpol/polarization.py
crystalpol/shared/__init__.py
crystalpol/shared/config/__init__.py
crystalpol/shared/config/config.py
crystalpol/shared/system/__init__.py
crystalpol/shared/system/atom.py
crystalpol/shared/system/crystal.py
crystalpol/shared/system/molecule.py
crystalpol/shared/utils/__init__.py
crystalpol/shared/utils/log.py
crystalpol/shared/utils/ptable.py
crystalpol-0.0.1.post5.dist-info/LICENSE
crystalpol-0.0.1.post5.dist-info/METADATA
crystalpol-0.0.1.post5.dist-info/WHEEL
crystalpol-0.0.1.post5.dist-info/entry_points.txt
crystalpol-0.0.1.post5.dist-info/RECORD
