Metadata-Version: 2.1
Name: crystalpol
Version: 0.0.1.post5
Summary: Crystal Optimization Automation using Gaussian16
License: GPL-2.0-only
Author: Vitor Hideyoshi
Author-email: vitor.h.n.batista@gmail.com
Requires-Python: >=3.8,<4.0
Classifier: License :: OSI Approved :: GNU General Public License v2 (GPLv2)
Classifier: Programming Language :: Python :: 3
Classifier: Programming Language :: Python :: 3.8
Classifier: Programming Language :: Python :: 3.9
Classifier: Programming Language :: Python :: 3.10
Classifier: Programming Language :: Python :: 3.11
Requires-Dist: PyYAML (>=6.0,<7.0)
Requires-Dist: setproctitle (>=1.3.2,<2.0.0)
